{
  "task_1767857673057_dc46k8w": {
    "service-templates": {
      "task_1767857673057_dc46k8w": {
        "fields": [
          "id"
        ],
        "score": 6,
        "lastUpdated": "2026-01-29T20:24:41.154Z"
      }
    }
  },
  "task_1767857673179_dadz36q": {
    "service-templates": {
      "task_1767857673179_dadz36q": {
        "fields": [
          "id"
        ],
        "score": 6,
        "lastUpdated": "2026-01-29T20:24:41.162Z"
      }
    }
  },
  "task_1767857673182_93pqypc": {
    "service-templates": {
      "task_1767857673182_93pqypc": {
        "fields": [
          "id"
        ],
        "score": 6,
        "lastUpdated": "2026-01-29T20:24:41.171Z"
      }
    }
  },
  "task_1767857673143_xe6s4z2": {
    "service-templates": {
      "task_1767857673143_xe6s4z2": {
        "fields": [
          "id"
        ],
        "score": 6,
        "lastUpdated": "2026-01-29T20:24:41.179Z"
      }
    }
  },
  "task_1767857673172_12jd07e": {
    "service-templates": {
      "task_1767857673172_12jd07e": {
        "fields": [
          "id"
        ],
        "score": 6,
        "lastUpdated": "2026-01-29T20:24:41.191Z"
      }
    }
  },
  "task_1767857673176_8eo017s": {
    "service-templates": {
      "task_1767857673176_8eo017s": {
        "fields": [
          "id"
        ],
        "score": 6,
        "lastUpdated": "2026-01-29T20:24:41.199Z"
      }
    }
  },
  "task_1767857673190_ltowj35": {
    "service-templates": {
      "task_1767857673190_ltowj35": {
        "fields": [
          "id"
        ],
        "score": 6,
        "lastUpdated": "2026-01-29T20:24:41.206Z"
      }
    }
  },
  "task_1767857673194_3szzgli": {
    "service-templates": {
      "task_1767857673194_3szzgli": {
        "fields": [
          "id"
        ],
        "score": 6,
        "lastUpdated": "2026-01-29T20:24:41.214Z"
      }
    }
  },
  "task_1769577711271_pt80ywd": {
    "service-templates": {
      "task_1769577711271_pt80ywd": {
        "fields": [
          "id"
        ],
        "score": 6,
        "lastUpdated": "2026-01-29T20:24:41.337Z"
      }
    }
  },
  "task_1769577711276_v43ft2w": {
    "service-templates": {
      "task_1769577711276_v43ft2w": {
        "fields": [
          "id"
        ],
        "score": 6,
        "lastUpdated": "2026-01-29T20:24:41.359Z"
      }
    }
  },
  "task_1769577711283_fadcc2g": {
    "service-templates": {
      "task_1769577711283_fadcc2g": {
        "fields": [
          "id"
        ],
        "score": 6,
        "lastUpdated": "2026-01-29T20:24:41.374Z"
      }
    }
  },
  "task_1769577711291_wwkixp9": {
    "service-templates": {
      "task_1769577711291_wwkixp9": {
        "fields": [
          "id"
        ],
        "score": 6,
        "lastUpdated": "2026-01-29T20:24:41.382Z"
      }
    }
  },
  "task_1769577711299_m70jcjg": {
    "service-templates": {
      "task_1769577711299_m70jcjg": {
        "fields": [
          "id"
        ],
        "score": 6,
        "lastUpdated": "2026-01-29T20:24:41.491Z"
      }
    }
  },
  "task_1769577711305_r29oiyd": {
    "service-templates": {
      "task_1769577711305_r29oiyd": {
        "fields": [
          "id"
        ],
        "score": 6,
        "lastUpdated": "2026-01-29T20:24:41.500Z"
      }
    }
  },
  "task_1769577711313_5js78wd": {
    "service-templates": {
      "task_1769577711313_5js78wd": {
        "fields": [
          "id"
        ],
        "score": 6,
        "lastUpdated": "2026-01-29T20:24:41.507Z"
      }
    }
  },
  "task_1769577711322_a5tr96p": {
    "service-templates": {
      "task_1769577711322_a5tr96p": {
        "fields": [
          "id"
        ],
        "score": 6,
        "lastUpdated": "2026-01-29T20:24:41.513Z"
      }
    }
  },
  "task_1769577711328_2onoxjc": {
    "service-templates": {
      "task_1769577711328_2onoxjc": {
        "fields": [
          "id"
        ],
        "score": 6,
        "lastUpdated": "2026-01-29T20:24:41.519Z"
      }
    }
  },
  "task_1769577711347_6gia7ju": {
    "service-templates": {
      "task_1769577711347_6gia7ju": {
        "fields": [
          "id"
        ],
        "score": 6,
        "lastUpdated": "2026-01-29T20:24:41.525Z"
      }
    }
  }
}